quantools/__init__.py
quantools/__version__.py
quantools/backtest.py
quantools/evaluate.py
quantools/indicator.py
quantools/rubust.py
quantools/utils.py
quantools-0.1.1.dist-info/LICENSE
quantools-0.1.1.dist-info/METADATA
quantools-0.1.1.dist-info/WHEEL
quantools-0.1.1.dist-info/top_level.txt
quantools-0.1.1.dist-info/RECORD
