Metadata-Version: 2.1
Name: quantools
Version: 0.1.1
Summary: 个人的量化指标计算与回测的工具库
Home-page: https://github.com/6YoungHome/Quantools
Author: 6Young
Author-email: 6young717@gmail.com
License: MIT
Classifier: License :: OSI Approved :: MIT License
Classifier: Programming Language :: Python
Classifier: Programming Language :: Python :: 3
Classifier: Programming Language :: Python :: 3.6
Classifier: Programming Language :: Python :: Implementation :: CPython
Classifier: Programming Language :: Python :: Implementation :: PyPy
Requires-Python: >=3.6.0
License-File: LICENSE
Requires-Dist: tqdm
Requires-Dist: matplotlib
Requires-Dist: pandas
Requires-Dist: numpy
Requires-Dist: statsmodels
Requires-Dist: sklearn
Requires-Dist: scipy
